rich_json_tree/__init__.py
rich_json_tree/tree.py
rich_json_tree-0.1.0.dist-info/licenses/LICENSE
rich_json_tree-0.1.0.dist-info/METADATA
rich_json_tree-0.1.0.dist-info/WHEEL
rich_json_tree-0.1.0.dist-info/top_level.txt
rich_json_tree-0.1.0.dist-info/RECORD
