Metadata-Version: 2.4
Name: rich-json-tree
Version: 0.1.0
Summary: Pretty JSON/tree viewer using Rich in the terminal
Author-email: Hritik Valluvar <hritikvalluvar@gmail.com>
License: MIT
Project-URL: Homepage, https://github.com/hritikvalluvar/rich-json-tree
Project-URL: Source, https://github.com/hritikvalluvar/rich-json-tree
Project-URL: Issues, https://github.com/hritikvalluvar/rich-json-tree/issues
Keywords: json,tree,rich,terminal,debugging
Requires-Python: >=3.8
License-File: LICENSE
Requires-Dist: rich>=13.0.0
Dynamic: license-file
